{
	"links" : {
		"welcome":{
			"title" : "Welcome",
			"path" : "/welcome",
			"iconCls" : "bi bi-house",
			"order": 1
		},
		"courses":{
			"title" : "Courses",
			"path" : "/course",
			"iconCls" : "bi bi-bookmark",
			"order" : 2,
			"hasChild" : true,
			"useModel" : true,
			"model" : "Course",
			"modelListMethod" : "getList",
			"displayField" : "title",
			"slugField" : "slug",
			"childRoutePath" : "/manager/{SLUG_VALUE}",
			"childIconCls" : "fa fa-bookmark-o"
		},
		"download" : {
			"title" : "Download",
			"path" : "/download",
			"iconCls" : "bi bi-download",
			"order" : 3,
			"hidden" : true
		},
		"setting" : {
			"title" : "Setting",
			"path" : "/setting",
			"iconCls" : "bi bi-gear",
			"order" : 4,
			"hidden" : true

		},
		"database" : {
			"title" : "Database Explorer",
			"path" : "/database",
			"iconCls" : "fa fa-database",
			"order" : 4,
			"hidden" : false,
			"hasChild" : true,
			"childItems" : {
				"download-state" : {
					"title" : "DownloadState",
					"path" : "/database/download-state",
					"iconCls" : "fa fa-database",
					"order" : 0
				},
				"download-config" : {
					"title" : "DownloadConfig",
					"path" : "/database/download-config",
					"iconCls" : "fa fa-database",
					"order" : 0
				},
				"course" : {
					"title" : "Course",
					"path" : "/database/course",
					"iconCls" : "fa fa-database",
					"order" : 0
				},
				"download" : {
					"title" : "Download",
					"path" : "/database/download",
					"iconCls" : "fa fa-database",
					"order" : 0
				},
				"dm-setup" : {
					"title" : "DMSetup",
					"path" : "/database/dm-setup",
					"iconCls" : "fa fa-database",
					"order" : 0
				}
			}
		},
		"bootstrap-icons" : {
			"title" : "Bootstrap Icons",
			"path" : "/bootstrap-icons",
			"iconCls" : "bi bi-bootstrap",
			"order" : 5,
			"hidden" : true

		}

	}
}